wrapitup/__init__.py
wrapitup/_catch_signals.py
wrapitup/_requests.py
wrapitup/_timer.py
wrapitup/_version.py
wrapitup/py.typed
wrapitup-0.3.0.dist-info/LICENSE
wrapitup-0.3.0.dist-info/METADATA
wrapitup-0.3.0.dist-info/WHEEL
wrapitup-0.3.0.dist-info/top_level.txt
wrapitup-0.3.0.dist-info/RECORD
